lab_utilities/__init__.py
lab_utilities/email.py
lab_utilities/equipment_config.py
lab_utilities/experimental_data_repository.py
lab_utilities/lab_git.py
lab_utilities/make_directory.py
lab_utilities/manifest_time_estimator.py
lab_utilities/package_to_text.py
lab_utilities/threading_utilities.py
lab_utilities-0.6.0.dist-info/LICENSE
lab_utilities-0.6.0.dist-info/METADATA
lab_utilities-0.6.0.dist-info/WHEEL
lab_utilities-0.6.0.dist-info/entry_points.txt
lab_utilities-0.6.0.dist-info/top_level.txt
lab_utilities-0.6.0.dist-info/RECORD
