Metadata-Version: 2.1
Name: lab-utilities
Version: 0.6.0
Summary: Lab Utilities
Home-page: https://github.com/stefangolas/lab_utilities.git
Author: Stefan Golas
Author-email: stefanmgolas@gmail.com
License: MIT
License-File: LICENSE
